{
    "intents": [
        {
            "tag": "CS 101",
            "patterns": [
                "When is CS 101 on my timetable?",
                "When is Introduction to Computer Science on my timetable?",
                "Which class do i have on Monday at 8:00 AM - 11:00 AM?",
                "When do i have CS 101?",
                "When do i have Introduction to Computer Science?",
                "When is CS 101?",
                "When is Introduction to Computer Science?"
            ],
            "responses": [
                "The class for CS 101: Introduction to Computer Science is at  8:00 AM - 11:00 AM on Monday at OH 12 by Mr. Kioko"
            ],
            "context_set": ""
        },
        {
            "tag": "CS 102",
            "patterns": [
                "When is CS 102 on my timetable?",
                "When is Introduction to Database Systems on my timetable?",
                "Which class do i have on Wednesday at 8:00 AM - 11:00 AM?",
                "When do i have CS 102?",
                "When do i have Introduction to Database Systems?",
                "When is CS 102?",
                "When is Introduction to Database Systems?"
            ],
            "responses": [
                "The class for CS 102: Introduction to Database Systems is at  8:00 AM - 11:00 AM on Wednesday at TH 12 by Mrs. Doreen"
            ],
            "context_set": ""
        },
        {
            "tag": "CS 104",
            "patterns": [
                "When is CS 104 on my timetable?",
                "When is Systems Analysis and Design on my timetable?",
                "Which class do i have on Monday at 11:00 AM - 2:00 PM?",
                "When do i have CS 104?",
                "When do i have Systems Analysis and Design?",
                "When is CS 104?",
                "When is Systems Analysis and Design?"
            ],
            "responses": [
                "The class for CS 104: Systems Analysis and Design is at  11:00 AM - 2:00 PM on Monday at OH 02 by Mr. Nichodemus"
            ],
            "context_set": ""
        },
        {
            "tag": "CS 105",
            "patterns": [
                "When is CS 105 on my timetable?",
                "When is Object Oriented Programming on my timetable?",
                "Which class do i have on Wednesday at 11:00 AM - 4:00 PM?",
                "When do i have CS 105?",
                "When do i have Object Oriented Programming?",
                "When is CS 105?",
                "When is Object Oriented Programming?"
            ],
            "responses": [
                "The class for CS 105: Object Oriented Programming is at  11:00 AM - 4:00 PM on Wednesday at OH 15 by Mr. Mwangi"
            ],
            "context_set": ""
        },
        {
            "tag": "CS 106",
            "patterns": [
                "When is CS 106 on my timetable?",
                "When is Mobile Application Development on my timetable?",
                "Which class do i have on Monday at 11:00 AM - 4:00 PM?",
                "When do i have CS 106?",
                "When do i have Mobile Application Development?",
                "When is CS 106?",
                "When is Mobile Application Development?"
            ],
            "responses": [
                "The class for CS 106: Mobile Application Development is at  11:00 AM - 4:00 PM on Monday at TH Lab B by Mr. Kibet"
            ],
            "context_set": ""
        }
    ]
}